{
  "Name": "3SBUF-1n",
  "NameLocation": 0,
  "ChipType": 0,
  "Size": {
    "x": 1.45,
    "y": 0.75
  },
  "Colour": {
    "r": 0.08925677,
    "g": 0.38920933,
    "b": 0.0163614061,
    "a": 1
  },
  "InputPins":[
    {
      "Name":"IN",
      "ID":317161122,
      "Position":{
        "x":-16.125,
        "y":2.0
      },
      "BitCount":4,
      "Colour":0,
      "ValueDisplayMode":0
    },
    {
      "Name":"ENABLE",
      "ID":1442735540,
      "Position":{
        "x":-16.125,
        "y":0.875
      },
      "BitCount":1,
      "Colour":1,
      "ValueDisplayMode":0
    }
  ],
  "OutputPins":[
    {
      "Name":"OUT",
      "ID":1993033448,
      "Position":{
        "x":-7.0,
        "y":1.8125
      },
      "BitCount":4,
      "Colour":0,
      "ValueDisplayMode":0
    },
    {
      "Name":"ENABLED",
      "ID":449598230,
      "Position":{
        "x":-7.0,
        "y":0.875
      },
      "BitCount":1,
      "Colour":0,
      "ValueDisplayMode":0
    }
  ],
  "SubChips":[
    {
      "Name":"3-STATE BUFFER",
      "ID":1435104733,
      "Label":"",
      "Position":{
        "x":-11.5,
        "y":3.6875
      },
      "OutputPinColourInfo":[{"PinColour":0,"PinID":2}],
      "InternalData":null
    },
    {
      "Name":"3-STATE BUFFER",
      "ID":1714522546,
      "Label":"",
      "Position":{
        "x":-11.5,
        "y":2.9375
      },
      "OutputPinColourInfo":[{"PinColour":0,"PinID":2}],
      "InternalData":null
    },
    {
      "Name":"3-STATE BUFFER",
      "ID":544765666,
      "Label":"",
      "Position":{
        "x":-11.5,
        "y":2.1875
      },
      "OutputPinColourInfo":[{"PinColour":0,"PinID":2}],
      "InternalData":null
    },
    {
      "Name":"3-STATE BUFFER",
      "ID":1511539636,
      "Label":"",
      "Position":{
        "x":-11.5,
        "y":1.4375
      },
      "OutputPinColourInfo":[{"PinColour":0,"PinID":2}],
      "InternalData":null
    },
    {
      "Name":"1-4BIT",
      "ID":800307346,
      "Label":"",
      "Position":{
        "x":-9.1775,
        "y":1.8125
      },
      "OutputPinColourInfo":[{"PinColour":0,"PinID":4}],
      "InternalData":null
    },
    {
      "Name":"4-1BIT",
      "ID":130020673,
      "Label":"",
      "Position":{
        "x":-14.0525,
        "y":2.0
      },
      "OutputPinColourInfo":[{"PinColour":0,"PinID":1},{"PinColour":0,"PinID":2},{"PinColour":0,"PinID":3},{"PinColour":0,"PinID":4}],
      "InternalData":null
    }
  ],
  "Wires":[
    {
      "SourcePinAddress":{
        "PinID":2,
        "PinOwnerID":1511539636
      },
      "TargetPinAddress":{
        "PinID":3,
        "PinOwnerID":800307346
      },
      "ConnectionType":0,
      "ConnectedWireIndex":-1,
      "ConnectedWireSegmentIndex":-1,
      "Points":[{"x":0.0,"y":0.0},{"x":0.0,"y":0.0}]
    },
    {
      "SourcePinAddress":{
        "PinID":4,
        "PinOwnerID":800307346
      },
      "TargetPinAddress":{
        "PinID":0,
        "PinOwnerID":1993033448
      },
      "ConnectionType":0,
      "ConnectedWireIndex":-1,
      "ConnectedWireSegmentIndex":-1,
      "Points":[{"x":0.0,"y":0.0},{"x":0.0,"y":0.0}]
    },
    {
      "SourcePinAddress":{
        "PinID":0,
        "PinOwnerID":317161122
      },
      "TargetPinAddress":{
        "PinID":0,
        "PinOwnerID":130020673
      },
      "ConnectionType":0,
      "ConnectedWireIndex":-1,
      "ConnectedWireSegmentIndex":-1,
      "Points":[{"x":0.0,"y":0.0},{"x":0.0,"y":0.0}]
    },
    {
      "SourcePinAddress":{
        "PinID":0,
        "PinOwnerID":1442735540
      },
      "TargetPinAddress":{
        "PinID":0,
        "PinOwnerID":449598230
      },
      "ConnectionType":0,
      "ConnectedWireIndex":-1,
      "ConnectedWireSegmentIndex":-1,
      "Points":[{"x":0.0,"y":0.0},{"x":0.0,"y":0.0}]
    },
    {
      "SourcePinAddress":{
        "PinID":0,
        "PinOwnerID":1442735540
      },
      "TargetPinAddress":{
        "PinID":1,
        "PinOwnerID":1435104733
      },
      "ConnectionType":1,
      "ConnectedWireIndex":3,
      "ConnectedWireSegmentIndex":0,
      "Points":[{"x":-12.5,"y":0.875},{"x":-12.5,"y":3.5},{"x":0.0,"y":0.0}]
    },
    {
      "SourcePinAddress":{
        "PinID":0,
        "PinOwnerID":1442735540
      },
      "TargetPinAddress":{
        "PinID":1,
        "PinOwnerID":1714522546
      },
      "ConnectionType":1,
      "ConnectedWireIndex":4,
      "ConnectedWireSegmentIndex":0,
      "Points":[{"x":-12.5,"y":2.75},{"x":0.0,"y":0.0}]
    },
    {
      "SourcePinAddress":{
        "PinID":0,
        "PinOwnerID":1442735540
      },
      "TargetPinAddress":{
        "PinID":1,
        "PinOwnerID":544765666
      },
      "ConnectionType":1,
      "ConnectedWireIndex":4,
      "ConnectedWireSegmentIndex":0,
      "Points":[{"x":-12.5,"y":2.0},{"x":0.0,"y":0.0}]
    },
    {
      "SourcePinAddress":{
        "PinID":0,
        "PinOwnerID":1442735540
      },
      "TargetPinAddress":{
        "PinID":1,
        "PinOwnerID":1511539636
      },
      "ConnectionType":1,
      "ConnectedWireIndex":4,
      "ConnectedWireSegmentIndex":0,
      "Points":[{"x":-12.5,"y":1.25},{"x":0.0,"y":0.0}]
    },
    {
      "SourcePinAddress":{
        "PinID":4,
        "PinOwnerID":130020673
      },
      "TargetPinAddress":{
        "PinID":0,
        "PinOwnerID":1511539636
      },
      "ConnectionType":0,
      "ConnectedWireIndex":-1,
      "ConnectedWireSegmentIndex":-1,
      "Points":[{"x":0.0,"y":0.0},{"x":0.0,"y":0.0}]
    },
    {
      "SourcePinAddress":{
        "PinID":3,
        "PinOwnerID":130020673
      },
      "TargetPinAddress":{
        "PinID":0,
        "PinOwnerID":544765666
      },
      "ConnectionType":0,
      "ConnectedWireIndex":-1,
      "ConnectedWireSegmentIndex":-1,
      "Points":[{"x":0.0,"y":0.0},{"x":-12.75,"y":1.875},{"x":-12.75,"y":2.375},{"x":0.0,"y":0.0}]
    },
    {
      "SourcePinAddress":{
        "PinID":2,
        "PinOwnerID":130020673
      },
      "TargetPinAddress":{
        "PinID":0,
        "PinOwnerID":1714522546
      },
      "ConnectionType":0,
      "ConnectedWireIndex":-1,
      "ConnectedWireSegmentIndex":-1,
      "Points":[{"x":0.0,"y":0.0},{"x":-13.0,"y":2.125},{"x":-13.0,"y":3.125},{"x":0.0,"y":0.0}]
    },
    {
      "SourcePinAddress":{
        "PinID":1,
        "PinOwnerID":130020673
      },
      "TargetPinAddress":{
        "PinID":0,
        "PinOwnerID":1435104733
      },
      "ConnectionType":0,
      "ConnectedWireIndex":-1,
      "ConnectedWireSegmentIndex":-1,
      "Points":[{"x":0.0,"y":0.0},{"x":-13.25,"y":2.375},{"x":-13.25,"y":3.875},{"x":0.0,"y":0.0}]
    },
    {
      "SourcePinAddress":{
        "PinID":2,
        "PinOwnerID":544765666
      },
      "TargetPinAddress":{
        "PinID":2,
        "PinOwnerID":800307346
      },
      "ConnectionType":0,
      "ConnectedWireIndex":-1,
      "ConnectedWireSegmentIndex":-1,
      "Points":[{"x":0.0,"y":0.0},{"x":-10.5,"y":2.1875},{"x":-10.5,"y":1.6875},{"x":0.0,"y":0.0}]
    },
    {
      "SourcePinAddress":{
        "PinID":2,
        "PinOwnerID":1714522546
      },
      "TargetPinAddress":{
        "PinID":1,
        "PinOwnerID":800307346
      },
      "ConnectionType":0,
      "ConnectedWireIndex":-1,
      "ConnectedWireSegmentIndex":-1,
      "Points":[{"x":0.0,"y":0.0},{"x":-10.3125,"y":2.9375},{"x":-10.3125,"y":1.9375},{"x":0.0,"y":0.0}]
    },
    {
      "SourcePinAddress":{
        "PinID":2,
        "PinOwnerID":1435104733
      },
      "TargetPinAddress":{
        "PinID":0,
        "PinOwnerID":800307346
      },
      "ConnectionType":0,
      "ConnectedWireIndex":-1,
      "ConnectedWireSegmentIndex":-1,
      "Points":[{"x":0.0,"y":0.0},{"x":-10.0625,"y":3.6875},{"x":-10.0625,"y":2.1875},{"x":0.0,"y":0.0}]
    }
  ],
  "Displays":[]
}